CheckUtil/CheckUtil.py
CheckUtil/__init__.py
CheckUtil-0.4.2.dist-info/METADATA
CheckUtil-0.4.2.dist-info/WHEEL
CheckUtil-0.4.2.dist-info/top_level.txt
CheckUtil-0.4.2.dist-info/RECORD
