Metadata-Version: 2.1
Name: CheckUtil
Version: 0.4.2
Summary: This package is use to check the RAM and CPU Usage of Current Device.
Home-page: https://github.com/Nidhi0829/CheckUtil
Author: Nidhi_Sharma
